pypore3d/__init__.py
pypore3d/_p3dBlob.cp311-win_amd64.pyd
pypore3d/_p3dFilt.cp311-win_amd64.pyd
pypore3d/_p3dSkel.cp311-win_amd64.pyd
pypore3d/p3dBlob.py
pypore3d/p3dBlobPy.py
pypore3d/p3dFilt.py
pypore3d/p3dFiltPy.py
pypore3d/p3dFiltPy_16.py
pypore3d/p3dSITKPy.py
pypore3d/p3dSITKPy_16.py
pypore3d/p3dSkel.py
pypore3d/p3dSkelPy.py
pypore3d/p3d_SITK_common_lib.py
pypore3d/p3d_SITK_common_lib_16.py
pypore3d/p3d_SITK_read_raw.py
pypore3d/p3d_common_lib.py
pypore3d_test-0.0.6.dist-info/LICENSE
pypore3d_test-0.0.6.dist-info/METADATA
pypore3d_test-0.0.6.dist-info/WHEEL
pypore3d_test-0.0.6.dist-info/top_level.txt
pypore3d_test-0.0.6.dist-info/RECORD
