Metadata-Version: 2.1
Name: pypore3d-test
Version: 0.0.6
Summary: Pore3d with python wrappers
Home-page: https://gitlab.elettra.eu/amal.abouelhassan/pore3d_py
Author: Amal Aboulhassan
Author-email: aboulhassan.amal@gmail.com
Classifier: Programming Language :: Python :: 3
Classifier: License :: OSI Approved :: MIT License
Classifier: Operating System :: OS Independent
Requires-Python: >=3.8, <3.12
License-File: LICENSE
